hayagriva/__init__.py
hayagriva/config.py
hayagriva/exceptions.py
hayagriva/version.py
hayagriva/cli/__init__.py
hayagriva/cli/cli.py
hayagriva/core/__init__.py
hayagriva/core/chunker.py
hayagriva/core/context_builder.py
hayagriva/core/embeddings.py
hayagriva/core/generator.py
hayagriva/core/groq_generator.py
hayagriva/core/hayagriva.py
hayagriva/core/pinecone_store.py
hayagriva/core/pipeline.py
hayagriva/core/retriever.py
hayagriva/core/vectorstore.py
hayagriva/core/weaviate_store.py
hayagriva/ingestion/__init__.py
hayagriva/ingestion/loaders.py
hayagriva/ingestion/metadata.py
hayagriva/ingestion/parser.py
hayagriva/utils/__init__.py
hayagriva/utils/cache.py
hayagriva/utils/file_ops.py
hayagriva/utils/logger.py
hayagriva/utils/tokens.py
hayagriva/utils/validator.py
hayagriva-0.2.4.dist-info/licenses/LICENSE
hayagriva-0.2.4.dist-info/METADATA
hayagriva-0.2.4.dist-info/WHEEL
hayagriva-0.2.4.dist-info/entry_points.txt
hayagriva-0.2.4.dist-info/top_level.txt
hayagriva-0.2.4.dist-info/RECORD
