Metadata-Version: 2.4
Name: hayagriva
Version: 0.2.4
Summary: Modular RAG framework with support for FAISS, Weaviate, and Hybrid Search.
Author: Hayagriva Team
License: MIT
Project-URL: Homepage, https://github.com/rajsimpi-ai/hayagriva
Requires-Python: >=3.10
License-File: LICENSE
Requires-Dist: numpy
Requires-Dist: openai>=1.0.0
Requires-Dist: groq
Requires-Dist: weaviate-client
Requires-Dist: pinecone-client
Provides-Extra: cpu
Requires-Dist: sentence-transformers; extra == "cpu"
Requires-Dist: faiss-cpu; extra == "cpu"
Provides-Extra: cuda
Requires-Dist: sentence-transformers; extra == "cuda"
Requires-Dist: faiss-gpu; extra == "cuda"
Dynamic: license-file
